un_treaties/__init__.py
un_treaties/crawler/__init__.py
un_treaties/crawler/countries.py
un_treaties/crawler/get_data.py
un_treaties/data/__init__.py
un_treaties/rest_api/__init__.py
un_treaties/rest_api/api.py
un_treaties/rest_api/chapter.py
un_treaties/rest_api/country.py
un_treaties/rest_api/swagger.yml
un_treaties/rest_api/treaty.py
un_treaties-0.1.2.dist-info/METADATA
un_treaties-0.1.2.dist-info/WHEEL
un_treaties-0.1.2.dist-info/entry_points.txt
un_treaties-0.1.2.dist-info/top_level.txt
un_treaties-0.1.2.dist-info/RECORD
