Metadata-Version: 2.1
Name: un-treaties
Version: 0.1.2
Summary: Push countries to ratify UN treaties
Home-page: https://github.com/DataForGood-Norway/un_treaties
Author: Data For Good - Norway
Author-email: contact@dataforgood.no
License: MIT
Platform: UNKNOWN
Classifier: License :: OSI Approved :: MIT License
Classifier: Programming Language :: Python :: 3
Classifier: Programming Language :: Python :: 3.6
Classifier: Programming Language :: Python :: 3.7
Requires-Dist: beautifulsoup4
Requires-Dist: connexion
Requires-Dist: html5lib
Requires-Dist: lxml
Requires-Dist: pandas
Requires-Dist: pycountry
Requires-Dist: requests
